Topsis/__init__.py
Topsis/__main__.py
Topsis_Aashim_102103401-1.0.dist-info/LICENSE
Topsis_Aashim_102103401-1.0.dist-info/METADATA
Topsis_Aashim_102103401-1.0.dist-info/WHEEL
Topsis_Aashim_102103401-1.0.dist-info/entry_points.txt
Topsis_Aashim_102103401-1.0.dist-info/top_level.txt
Topsis_Aashim_102103401-1.0.dist-info/RECORD
