Metadata-Version: 2.1
Name: Topsis-Aashim-102103401
Version: 1.0
Summary: Topsis-Aashim-102103401
Author: Aashim Bansal
Author-email: aashimbansal2003@gmail.com
License: MIT
Classifier: License :: OSI Approved :: MIT License
Classifier: Programming Language :: Python :: 3.6
Classifier: Programming Language :: Python :: 3.7
Classifier: Programming Language :: Python :: 3.8
License-File: LICENSE
